adafruit_adxl34x.py
adafruit_circuitpython_adxl34x-1.12.18.dist-info/licenses/LICENSE
adafruit_circuitpython_adxl34x-1.12.18.dist-info/METADATA
adafruit_circuitpython_adxl34x-1.12.18.dist-info/WHEEL
adafruit_circuitpython_adxl34x-1.12.18.dist-info/top_level.txt
adafruit_circuitpython_adxl34x-1.12.18.dist-info/RECORD
